{"nodes": [{"id": "procedure_cohort_pipeline", "label": "Cohort-Based Pavement Trajectory Analysis Pipeline", "file_type": "document", "source_file": "procedure.md", "source_location": null, "source_url": null, "captured_at": null, "author": null, "contributor": null}, {"id": "procedure_section_entity", "label": "Highway Section Entity (half-mile segment)", "file_type": "concept", "source_file": "procedure.md", "source_location": null, "source_url": null, "captured_at": null, "author": null, "contributor": null}, {"id": "procedure_section_year_matrix", "label": "Section x Year Condition Matrix", "file_type": "concept", "source_file": "procedure.md", "source_location": null, "source_url": null, "captured_at": null, "author": null, "contributor": null}, {"id": "procedure_preserve_gaps", "label": "Preserve Gaps (No Interpolation)", "file_type": "rationale", "source_file": "procedure.md", "source_location": null, "source_url": null, "captured_at": null, "author": null, "contributor": null}, {"id": "procedure_sliding_window", "label": "Sliding Multi-Year Window (W)", "file_type": "concept", "source_file": "procedure.md", "source_location": null, "source_url": null, "captured_at": null, "author": null, "contributor": null}, {"id": "procedure_window_normalize", "label": "Within-Window Trajectory Normalization", "file_type": "concept", "source_file": "procedure.md", "source_location": null, "source_url": null, "captured_at": null, "author": null, "contributor": null}, {"id": "procedure_pairwise_pearson", "label": "Pairwise-Complete Pearson Trend Similarity", "file_type": "concept", "source_file": "procedure.md", "source_location": null, "source_url": null, "captured_at": null, "author": null, "contributor": null}, {"id": "procedure_threshold_binary", "label": "Binary Correlation Threshold (thr)", "file_type": "concept", "source_file": "procedure.md", "source_location": null, "source_url": null, "captured_at": null, "author": null, "contributor": null}, {"id": "procedure_spatial_proximity", "label": "Binary Spatial Proximity Rule", "file_type": "concept", "source_file": "procedure.md", "source_location": null, "source_url": null, "captured_at": null, "author": null, "contributor": null}, {"id": "procedure_relation_network", "label": "Per-Window Relation Network (intersection of filters)", "file_type": "concept", "source_file": "procedure.md", "source_location": null, "source_url": null, "captured_at": null, "author": null, "contributor": null}, {"id": "procedure_louvain", "label": "Louvain Community Detection", "file_type": "concept", "source_file": "procedure.md", "source_location": null, "source_url": null, "captured_at": null, "author": null, "contributor": null}, {"id": "procedure_session_filter", "label": "Small Session Filtering (ths)", "file_type": "concept", "source_file": "procedure.md", "source_location": null, "source_url": null, "captured_at": null, "author": null, "contributor": null}, {"id": "procedure_session_tracking", "label": "Cross-Window Session Tracking (max overlap)", "file_type": "concept", "source_file": "procedure.md", "source_location": null, "source_url": null, "captured_at": null, "author": null, "contributor": null}, {"id": "procedure_treatment_events", "label": "Treatment Event Detection (rehab/overlay jumps)", "file_type": "concept", "source_file": "procedure.md", "source_location": null, "source_url": null, "captured_at": null, "author": null, "contributor": null}, {"id": "procedure_validation", "label": "Validation (ARI/purity, cohort stability)", "file_type": "concept", "source_file": "procedure.md", "source_location": null, "source_url": null, "captured_at": null, "author": null, "contributor": null}, {"id": "procedure_two_level_viz", "label": "Two-Level Visualization (Storyline + EvoLens)", "file_type": "concept", "source_file": "procedure.md", "source_location": null, "source_url": null, "captured_at": null, "author": null, "contributor": null}], "edges": [{"source": "procedure_cohort_pipeline", "target": "paper_geochron", "relation": "references", "confidence": "EXTRACTED", "confidence_score": 1.0, "source_file": "procedure.md", "source_location": null, "weight": 1.0}, {"source": "procedure_cohort_pipeline", "target": "procedure_section_entity", "relation": "conceptually_related_to", "confidence": "EXTRACTED", "confidence_score": 1.0, "source_file": "procedure.md", "source_location": null, "weight": 1.0}, {"source": "procedure_section_entity", "target": "procedure_section_year_matrix", "relation": "conceptually_related_to", "confidence": "EXTRACTED", "confidence_score": 1.0, "source_file": "procedure.md", "source_location": null, "weight": 1.0}, {"source": "procedure_section_year_matrix", "target": "procedure_preserve_gaps", "relation": "conceptually_related_to", "confidence": "EXTRACTED", "confidence_score": 1.0, "source_file": "procedure.md", "source_location": null, "weight": 1.0}, {"source": "procedure_sliding_window", "target": "procedure_window_normalize", "relation": "conceptually_related_to", "confidence": "EXTRACTED", "confidence_score": 1.0, "source_file": "procedure.md", "source_location": null, "weight": 1.0}, {"source": "procedure_window_normalize", "target": "procedure_pairwise_pearson", "relation": "conceptually_related_to", "confidence": "EXTRACTED", "confidence_score": 1.0, "source_file": "procedure.md", "source_location": null, "weight": 1.0}, {"source": "procedure_pairwise_pearson", "target": "procedure_threshold_binary", "relation": "conceptually_related_to", "confidence": "EXTRACTED", "confidence_score": 1.0, "source_file": "procedure.md", "source_location": null, "weight": 1.0}, {"source": "procedure_relation_network", "target": "procedure_threshold_binary", "relation": "conceptually_related_to", "confidence": "EXTRACTED", "confidence_score": 1.0, "source_file": "procedure.md", "source_location": null, "weight": 1.0}, {"source": "procedure_relation_network", "target": "procedure_spatial_proximity", "relation": "conceptually_related_to", "confidence": "EXTRACTED", "confidence_score": 1.0, "source_file": "procedure.md", "source_location": null, "weight": 1.0}, {"source": "procedure_louvain", "target": "procedure_relation_network", "relation": "conceptually_related_to", "confidence": "EXTRACTED", "confidence_score": 1.0, "source_file": "procedure.md", "source_location": null, "weight": 1.0}, {"source": "procedure_session_filter", "target": "procedure_louvain", "relation": "conceptually_related_to", "confidence": "EXTRACTED", "confidence_score": 1.0, "source_file": "procedure.md", "source_location": null, "weight": 1.0}, {"source": "procedure_session_tracking", "target": "procedure_session_filter", "relation": "conceptually_related_to", "confidence": "EXTRACTED", "confidence_score": 1.0, "source_file": "procedure.md", "source_location": null, "weight": 1.0}, {"source": "procedure_treatment_events", "target": "procedure_session_tracking", "relation": "conceptually_related_to", "confidence": "EXTRACTED", "confidence_score": 1.0, "source_file": "procedure.md", "source_location": null, "weight": 1.0}, {"source": "procedure_louvain", "target": "paper_pattern_mining_framework", "relation": "references", "confidence": "EXTRACTED", "confidence_score": 1.0, "source_file": "procedure.md", "source_location": null, "weight": 1.0}, {"source": "procedure_two_level_viz", "target": "paper_storyline", "relation": "references", "confidence": "EXTRACTED", "confidence_score": 1.0, "source_file": "procedure.md", "source_location": null, "weight": 1.0}, {"source": "procedure_two_level_viz", "target": "paper_evolens", "relation": "references", "confidence": "EXTRACTED", "confidence_score": 1.0, "source_file": "procedure.md", "source_location": null, "weight": 1.0}, {"source": "procedure_sliding_window", "target": "paper_wrapping_window", "relation": "semantically_similar_to", "confidence": "INFERRED", "confidence_score": 0.85, "source_file": "procedure.md", "source_location": null, "weight": 1.0}, {"source": "procedure_relation_network", "target": "paper_network_formulation", "relation": "semantically_similar_to", "confidence": "INFERRED", "confidence_score": 0.85, "source_file": "procedure.md", "source_location": null, "weight": 1.0}], "hyperedges": [{"id": "geochron_pattern_mining_flow", "label": "Evolution Pattern Mining Flow", "nodes": ["procedure_pairwise_pearson", "procedure_relation_network", "procedure_louvain"], "relation": "form", "confidence": "INFERRED", "confidence_score": 0.85, "source_file": "procedure.md"}, {"id": "geochron_windowing_pipeline", "label": "Windowing and Similarity Pipeline", "nodes": ["procedure_sliding_window", "procedure_window_normalize", "procedure_threshold_binary"], "relation": "participate_in", "confidence": "INFERRED", "confidence_score": 0.75, "source_file": "procedure.md"}]}