{"nodes": [{"id": "index_county_page", "label": "Storyline by County Only (index_county)", "file_type": "document", "source_file": "index_county.html", "source_location": null, "source_url": null, "captured_at": null, "author": null, "contributor": null}], "edges": [{"source": "index_county_page", "target": "storyline_canvas_viz", "relation": "references", "confidence": "EXTRACTED", "confidence_score": 1.0, "source_file": "index_county.html", "source_location": null, "weight": 1.0}, {"source": "index_county_page", "target": "index_page", "relation": "references", "confidence": "EXTRACTED", "confidence_score": 1.0, "source_file": "index_county.html", "source_location": null, "weight": 1.0}], "hyperedges": []}