{"nodes": [{"id": "c_users_owner_documents_geochron_build_unit_heatmaps_nofill_py", "label": "build_unit_heatmaps_nofill.py", "file_type": "code", "source_file": "build_unit_heatmaps_nofill.py", "source_location": "L1"}, {"id": "c_users_owner_documents_geochron_build_unit_heatmaps_nofill_rationale_1", "label": "Variant of build_unit_heatmaps.py using NO gap fill (\"option 2\"), for comparison", "file_type": "rationale", "source_file": "build_unit_heatmaps_nofill.py", "source_location": "L1"}], "edges": [{"source": "c_users_owner_documents_geochron_build_unit_heatmaps_nofill_py", "target": "json", "relation": "imports", "context": "import", "confidence": "EXTRACTED", "source_file": "build_unit_heatmaps_nofill.py", "source_location": "L14", "weight": 1.0}, {"source": "c_users_owner_documents_geochron_build_unit_heatmaps_nofill_py", "target": "warnings", "relation": "imports", "context": "import", "confidence": "EXTRACTED", "source_file": "build_unit_heatmaps_nofill.py", "source_location": "L15", "weight": 1.0}, {"source": "c_users_owner_documents_geochron_build_unit_heatmaps_nofill_py", "target": "numpy", "relation": "imports", "context": "import", "confidence": "EXTRACTED", "source_file": "build_unit_heatmaps_nofill.py", "source_location": "L16", "weight": 1.0}, {"source": "c_users_owner_documents_geochron_build_unit_heatmaps_nofill_rationale_1", "target": "c_users_owner_documents_geochron_build_unit_heatmaps_nofill_py", "relation": "rationale_for", "confidence": "EXTRACTED", "source_file": "build_unit_heatmaps_nofill.py", "source_location": "L1", "weight": 1.0}], "raw_calls": []}